[
  {
    "title": "Industrial Adhesives & Tapes Specialist, Northern California",
    "company": "",
    "location": "",
    "date_posted": "",
    "apply_url": "https://3m.wd1.myworkdayjobs.com/en-US/Search/job/Remote---California/Industrial-Adhesives---Tapes-Specialist--Northern-California_R01155033",
    "description": "",
    "salary": "",
    "job_type": "",
    "source_site": "3M Workday",
    "scraped_at": "2025-10-07T10:48:51.584863"
  },
  {
    "title": "Industrial Adhesives & Tapes Specialist, Northern California",
    "company": "",
    "location": "",
    "date_posted": "",
    "apply_url": "https://3m.wd1.myworkdayjobs.com/en-US/Search/job/Remote---California/Industrial-Adhesives---Tapes-Specialist--Northern-California_R01155033",
    "description": "",
    "salary": "",
    "job_type": "",
    "source_site": "3M Workday",
    "scraped_at": "2025-10-07T10:48:51.586868"
  },
  {
    "title": "Industrial Adhesives & Tapes Specialist, Northern California",
    "company": "",
    "location": "",
    "date_posted": "",
    "apply_url": "https://3m.wd1.myworkdayjobs.com/en-US/Search/job/Remote---California/Industrial-Adhesives---Tapes-Specialist--Northern-California_R01155033",
    "description": "",
    "salary": "",
    "job_type": "",
    "source_site": "3M Workday",
    "scraped_at": "2025-10-07T10:48:51.587869"
  },
  {
    "title": "Spezialist Produktionssysteme / Fertigung (m/w/*)",
    "company": "",
    "location": "",
    "date_posted": "",
    "apply_url": "https://3m.wd1.myworkdayjobs.com/en-US/Search/job/DE-North-Rhine-Westphalia-Hilden/Spezialist-Produktionssysteme---Fertigung--m-w---_R01156441-2",
    "description": "",
    "salary": "",
    "job_type": "",
    "source_site": "3M Workday",
    "scraped_at": "2025-10-07T10:48:51.589935"
  },
  {
    "title": "Spezialist Produktionssysteme / Fertigung (m/w/*)",
    "company": "",
    "location": "",
    "date_posted": "",
    "apply_url": "https://3m.wd1.myworkdayjobs.com/en-US/Search/job/DE-North-Rhine-Westphalia-Hilden/Spezialist-Produktionssysteme---Fertigung--m-w---_R01156441-2",
    "description": "",
    "salary": "",
    "job_type": "",
    "source_site": "3M Workday",
    "scraped_at": "2025-10-07T10:48:51.590972"
  },
  {
    "title": "Spezialist Produktionssysteme / Fertigung (m/w/*)",
    "company": "",
    "location": "",
    "date_posted": "",
    "apply_url": "https://3m.wd1.myworkdayjobs.com/en-US/Search/job/DE-North-Rhine-Westphalia-Hilden/Spezialist-Produktionssysteme---Fertigung--m-w---_R01156441-2",
    "description": "",
    "salary": "",
    "job_type": "",
    "source_site": "3M Workday",
    "scraped_at": "2025-10-07T10:48:51.592970"
  },
  {
    "title": "Shift Supervisor (m/v/*)",
    "company": "",
    "location": "",
    "date_posted": "",
    "apply_url": "https://3m.wd1.myworkdayjobs.com/en-US/Search/job/BE-Zwijndrecht/Shift-Supervisor--m-v---_R01156676",
    "description": "",
    "salary": "",
    "job_type": "",
    "source_site": "3M Workday",
    "scraped_at": "2025-10-07T10:48:51.594968"
  },
  {
    "title": "Shift Supervisor (m/v/*)",
    "company": "",
    "location": "",
    "date_posted": "",
    "apply_url": "https://3m.wd1.myworkdayjobs.com/en-US/Search/job/BE-Zwijndrecht/Shift-Supervisor--m-v---_R01156676",
    "description": "",
    "salary": "",
    "job_type": "",
    "source_site": "3M Workday",
    "scraped_at": "2025-10-07T10:48:51.595975"
  },
  {
    "title": "Shift Supervisor (m/v/*)",
    "company": "",
    "location": "",
    "date_posted": "",
    "apply_url": "https://3m.wd1.myworkdayjobs.com/en-US/Search/job/BE-Zwijndrecht/Shift-Supervisor--m-v---_R01156676",
    "description": "",
    "salary": "",
    "job_type": "",
    "source_site": "3M Workday",
    "scraped_at": "2025-10-07T10:48:51.596983"
  },
  {
    "title": "Product Content Senior Analyst - Sumaré/SP",
    "company": "",
    "location": "",
    "date_posted": "",
    "apply_url": "https://3m.wd1.myworkdayjobs.com/en-US/Search/job/BR-So-Paulo-Sumare/Product-Content-Senior-Analyst---Sumar-SP_R01156758",
    "description": "",
    "salary": "",
    "job_type": "",
    "source_site": "3M Workday",
    "scraped_at": "2025-10-07T10:48:51.598986"
  },
  {
    "title": "Product Content Senior Analyst - Sumaré/SP",
    "company": "",
    "location": "",
    "date_posted": "",
    "apply_url": "https://3m.wd1.myworkdayjobs.com/en-US/Search/job/BR-So-Paulo-Sumare/Product-Content-Senior-Analyst---Sumar-SP_R01156758",
    "description": "",
    "salary": "",
    "job_type": "",
    "source_site": "3M Workday",
    "scraped_at": "2025-10-07T10:48:51.599986"
  },
  {
    "title": "Product Content Senior Analyst - Sumaré/SP",
    "company": "",
    "location": "",
    "date_posted": "",
    "apply_url": "https://3m.wd1.myworkdayjobs.com/en-US/Search/job/BR-So-Paulo-Sumare/Product-Content-Senior-Analyst---Sumar-SP_R01156758",
    "description": "",
    "salary": "",
    "job_type": "",
    "source_site": "3M Workday",
    "scraped_at": "2025-10-07T10:48:51.600990"
  },
  {
    "title": "Strategy and Business Development Manager",
    "company": "",
    "location": "",
    "date_posted": "",
    "apply_url": "https://3m.wd1.myworkdayjobs.com/en-US/Search/job/US-Minnesota-Maplewood/Strategy-and-Business-Development-Manager_R01156383",
    "description": "",
    "salary": "",
    "job_type": "",
    "source_site": "3M Workday",
    "scraped_at": "2025-10-07T10:48:51.601969"
  },
  {
    "title": "Strategy and Business Development Manager",
    "company": "",
    "location": "",
    "date_posted": "",
    "apply_url": "https://3m.wd1.myworkdayjobs.com/en-US/Search/job/US-Minnesota-Maplewood/Strategy-and-Business-Development-Manager_R01156383",
    "description": "",
    "salary": "",
    "job_type": "",
    "source_site": "3M Workday",
    "scraped_at": "2025-10-07T10:48:51.604294"
  },
  {
    "title": "Strategy and Business Development Manager",
    "company": "",
    "location": "",
    "date_posted": "",
    "apply_url": "https://3m.wd1.myworkdayjobs.com/en-US/Search/job/US-Minnesota-Maplewood/Strategy-and-Business-Development-Manager_R01156383",
    "description": "",
    "salary": "",
    "job_type": "",
    "source_site": "3M Workday",
    "scraped_at": "2025-10-07T10:48:51.605297"
  },
  {
    "title": "Vertriebsmitarbeiter Außendienst (m/w/*) im Gebiet Mitte Deutschland",
    "company": "",
    "location": "",
    "date_posted": "",
    "apply_url": "https://3m.wd1.myworkdayjobs.com/en-US/Search/job/Remote-Germany/Vertriebsmitarbeiter-Auendienst--m-w----im-Gebiet-Mitte-Deutschland_R01156116-2",
    "description": "",
    "salary": "",
    "job_type": "",
    "source_site": "3M Workday",
    "scraped_at": "2025-10-07T10:48:51.606304"
  },
  {
    "title": "Vertriebsmitarbeiter Außendienst (m/w/*) im Gebiet Mitte Deutschland",
    "company": "",
    "location": "",
    "date_posted": "",
    "apply_url": "https://3m.wd1.myworkdayjobs.com/en-US/Search/job/Remote-Germany/Vertriebsmitarbeiter-Auendienst--m-w----im-Gebiet-Mitte-Deutschland_R01156116-2",
    "description": "",
    "salary": "",
    "job_type": "",
    "source_site": "3M Workday",
    "scraped_at": "2025-10-07T10:48:51.608309"
  },
  {
    "title": "Vertriebsmitarbeiter Außendienst (m/w/*) im Gebiet Mitte Deutschland",
    "company": "",
    "location": "",
    "date_posted": "",
    "apply_url": "https://3m.wd1.myworkdayjobs.com/en-US/Search/job/Remote-Germany/Vertriebsmitarbeiter-Auendienst--m-w----im-Gebiet-Mitte-Deutschland_R01156116-2",
    "description": "",
    "salary": "",
    "job_type": "",
    "source_site": "3M Workday",
    "scraped_at": "2025-10-07T10:48:51.609293"
  },
  {
    "title": "Business Development Manager – Militärmarkt (m/w/*)",
    "company": "",
    "location": "",
    "date_posted": "",
    "apply_url": "https://3m.wd1.myworkdayjobs.com/en-US/Search/job/DE-Neuss/Business-Development-Manager---Militrmarkt--m-w---_R01156515-1",
    "description": "",
    "salary": "",
    "job_type": "",
    "source_site": "3M Workday",
    "scraped_at": "2025-10-07T10:48:51.610806"
  },
  {
    "title": "Business Development Manager – Militärmarkt (m/w/*)",
    "company": "",
    "location": "",
    "date_posted": "",
    "apply_url": "https://3m.wd1.myworkdayjobs.com/en-US/Search/job/DE-Neuss/Business-Development-Manager---Militrmarkt--m-w---_R01156515-1",
    "description": "",
    "salary": "",
    "job_type": "",
    "source_site": "3M Workday",
    "scraped_at": "2025-10-07T10:48:51.611850"
  },
  {
    "title": "Business Development Manager – Militärmarkt (m/w/*)",
    "company": "",
    "location": "",
    "date_posted": "",
    "apply_url": "https://3m.wd1.myworkdayjobs.com/en-US/Search/job/DE-Neuss/Business-Development-Manager---Militrmarkt--m-w---_R01156515-1",
    "description": "",
    "salary": "",
    "job_type": "",
    "source_site": "3M Workday",
    "scraped_at": "2025-10-07T10:48:51.612864"
  },
  {
    "title": "Engineering Systems IT Architect",
    "company": "",
    "location": "",
    "date_posted": "",
    "apply_url": "https://3m.wd1.myworkdayjobs.com/en-US/Search/job/US-Minnesota-Maplewood/Engineering-Systems-IT-Architect_R01156531",
    "description": "",
    "salary": "",
    "job_type": "",
    "source_site": "3M Workday",
    "scraped_at": "2025-10-07T10:48:51.614867"
  },
  {
    "title": "Engineering Systems IT Architect",
    "company": "",
    "location": "",
    "date_posted": "",
    "apply_url": "https://3m.wd1.myworkdayjobs.com/en-US/Search/job/US-Minnesota-Maplewood/Engineering-Systems-IT-Architect_R01156531",
    "description": "",
    "salary": "",
    "job_type": "",
    "source_site": "3M Workday",
    "scraped_at": "2025-10-07T10:48:51.615867"
  },
  {
    "title": "Engineering Systems IT Architect",
    "company": "",
    "location": "",
    "date_posted": "",
    "apply_url": "https://3m.wd1.myworkdayjobs.com/en-US/Search/job/US-Minnesota-Maplewood/Engineering-Systems-IT-Architect_R01156531",
    "description": "",
    "salary": "",
    "job_type": "",
    "source_site": "3M Workday",
    "scraped_at": "2025-10-07T10:48:51.616867"
  },
  {
    "title": "Automotive Application Engineer - Battery Bonding",
    "company": "",
    "location": "",
    "date_posted": "",
    "apply_url": "https://3m.wd1.myworkdayjobs.com/en-US/Search/job/US-Michigan-Livonia/Automotive-Application-Engineer---Battery_R01150671",
    "description": "",
    "salary": "",
    "job_type": "",
    "source_site": "3M Workday",
    "scraped_at": "2025-10-07T10:48:51.617867"
  },
  {
    "title": "Automotive Application Engineer - Battery Bonding",
    "company": "",
    "location": "",
    "date_posted": "",
    "apply_url": "https://3m.wd1.myworkdayjobs.com/en-US/Search/job/US-Michigan-Livonia/Automotive-Application-Engineer---Battery_R01150671",
    "description": "",
    "salary": "",
    "job_type": "",
    "source_site": "3M Workday",
    "scraped_at": "2025-10-07T10:48:51.618867"
  },
  {
    "title": "Automotive Application Engineer - Battery Bonding",
    "company": "",
    "location": "",
    "date_posted": "",
    "apply_url": "https://3m.wd1.myworkdayjobs.com/en-US/Search/job/US-Michigan-Livonia/Automotive-Application-Engineer---Battery_R01150671",
    "description": "",
    "salary": "",
    "job_type": "",
    "source_site": "3M Workday",
    "scraped_at": "2025-10-07T10:48:51.620013"
  },
  {
    "title": "Global Labor Relations Director",
    "company": "",
    "location": "",
    "date_posted": "",
    "apply_url": "https://3m.wd1.myworkdayjobs.com/en-US/Search/job/US-Minnesota-Maplewood/Global-Labor-Relations-Director_R01156830",
    "description": "",
    "salary": "",
    "job_type": "",
    "source_site": "3M Workday",
    "scraped_at": "2025-10-07T10:48:51.622175"
  },
  {
    "title": "Global Labor Relations Director",
    "company": "",
    "location": "",
    "date_posted": "",
    "apply_url": "https://3m.wd1.myworkdayjobs.com/en-US/Search/job/US-Minnesota-Maplewood/Global-Labor-Relations-Director_R01156830",
    "description": "",
    "salary": "",
    "job_type": "",
    "source_site": "3M Workday",
    "scraped_at": "2025-10-07T10:48:51.623658"
  },
  {
    "title": "Global Labor Relations Director",
    "company": "",
    "location": "",
    "date_posted": "",
    "apply_url": "https://3m.wd1.myworkdayjobs.com/en-US/Search/job/US-Minnesota-Maplewood/Global-Labor-Relations-Director_R01156830",
    "description": "",
    "salary": "",
    "job_type": "",
    "source_site": "3M Workday",
    "scraped_at": "2025-10-07T10:48:51.624657"
  },
  {
    "title": "Environmental Engineer* (Cordova, IL)",
    "company": "",
    "location": "",
    "date_posted": "",
    "apply_url": "https://3m.wd1.myworkdayjobs.com/en-US/Search/job/US-Illinois-Cordova/Environmental-Engineer---Cordova--IL-_R01156825",
    "description": "",
    "salary": "",
    "job_type": "",
    "source_site": "3M Workday",
    "scraped_at": "2025-10-07T10:48:51.627504"
  },
  {
    "title": "Environmental Engineer* (Cordova, IL)",
    "company": "",
    "location": "",
    "date_posted": "",
    "apply_url": "https://3m.wd1.myworkdayjobs.com/en-US/Search/job/US-Illinois-Cordova/Environmental-Engineer---Cordova--IL-_R01156825",
    "description": "",
    "salary": "",
    "job_type": "",
    "source_site": "3M Workday",
    "scraped_at": "2025-10-07T10:48:51.628548"
  },
  {
    "title": "Environmental Engineer* (Cordova, IL)",
    "company": "",
    "location": "",
    "date_posted": "",
    "apply_url": "https://3m.wd1.myworkdayjobs.com/en-US/Search/job/US-Illinois-Cordova/Environmental-Engineer---Cordova--IL-_R01156825",
    "description": "",
    "salary": "",
    "job_type": "",
    "source_site": "3M Workday",
    "scraped_at": "2025-10-07T10:48:51.629553"
  },
  {
    "title": "Sr. Manager, Site Operations",
    "company": "",
    "location": "",
    "date_posted": "",
    "apply_url": "https://3m.wd1.myworkdayjobs.com/en-US/Search/job/US-Kentucky-Cynthiana/Sr-Manager--Site-Operations_R01156705",
    "description": "",
    "salary": "",
    "job_type": "",
    "source_site": "3M Workday",
    "scraped_at": "2025-10-07T10:48:51.631050"
  },
  {
    "title": "Sr. Manager, Site Operations",
    "company": "",
    "location": "",
    "date_posted": "",
    "apply_url": "https://3m.wd1.myworkdayjobs.com/en-US/Search/job/US-Kentucky-Cynthiana/Sr-Manager--Site-Operations_R01156705",
    "description": "",
    "salary": "",
    "job_type": "",
    "source_site": "3M Workday",
    "scraped_at": "2025-10-07T10:48:51.632104"
  },
  {
    "title": "Sr. Manager, Site Operations",
    "company": "",
    "location": "",
    "date_posted": "",
    "apply_url": "https://3m.wd1.myworkdayjobs.com/en-US/Search/job/US-Kentucky-Cynthiana/Sr-Manager--Site-Operations_R01156705",
    "description": "",
    "salary": "",
    "job_type": "",
    "source_site": "3M Workday",
    "scraped_at": "2025-10-07T10:48:51.633109"
  },
  {
    "title": "Vertriebsmitarbeiter Außendienst (m/w/*) im Gebiet Hessen / Nord-Bayern",
    "company": "",
    "location": "",
    "date_posted": "",
    "apply_url": "https://3m.wd1.myworkdayjobs.com/en-US/Search/job/Remote-Germany/Vertriebsmitarbeiter-Auendienst--m-w----im-Gebiet-Hessen---Nord-Bayern_R01156107-2",
    "description": "",
    "salary": "",
    "job_type": "",
    "source_site": "3M Workday",
    "scraped_at": "2025-10-07T10:48:51.634109"
  },
  {
    "title": "Vertriebsmitarbeiter Außendienst (m/w/*) im Gebiet Hessen / Nord-Bayern",
    "company": "",
    "location": "",
    "date_posted": "",
    "apply_url": "https://3m.wd1.myworkdayjobs.com/en-US/Search/job/Remote-Germany/Vertriebsmitarbeiter-Auendienst--m-w----im-Gebiet-Hessen---Nord-Bayern_R01156107-2",
    "description": "",
    "salary": "",
    "job_type": "",
    "source_site": "3M Workday",
    "scraped_at": "2025-10-07T10:48:51.636082"
  },
  {
    "title": "Vertriebsmitarbeiter Außendienst (m/w/*) im Gebiet Hessen / Nord-Bayern",
    "company": "",
    "location": "",
    "date_posted": "",
    "apply_url": "https://3m.wd1.myworkdayjobs.com/en-US/Search/job/Remote-Germany/Vertriebsmitarbeiter-Auendienst--m-w----im-Gebiet-Hessen---Nord-Bayern_R01156107-2",
    "description": "",
    "salary": "",
    "job_type": "",
    "source_site": "3M Workday",
    "scraped_at": "2025-10-07T10:48:51.636082"
  },
  {
    "title": "Process Development Engineer",
    "company": "",
    "location": "",
    "date_posted": "",
    "apply_url": "https://3m.wd1.myworkdayjobs.com/en-US/Search/job/US-Minnesota-Maplewood/Process-Development-Engineer_R01155761",
    "description": "",
    "salary": "",
    "job_type": "",
    "source_site": "3M Workday",
    "scraped_at": "2025-10-07T10:48:51.638568"
  },
  {
    "title": "Process Development Engineer",
    "company": "",
    "location": "",
    "date_posted": "",
    "apply_url": "https://3m.wd1.myworkdayjobs.com/en-US/Search/job/US-Minnesota-Maplewood/Process-Development-Engineer_R01155761",
    "description": "",
    "salary": "",
    "job_type": "",
    "source_site": "3M Workday",
    "scraped_at": "2025-10-07T10:48:51.639562"
  },
  {
    "title": "Process Development Engineer",
    "company": "",
    "location": "",
    "date_posted": "",
    "apply_url": "https://3m.wd1.myworkdayjobs.com/en-US/Search/job/US-Minnesota-Maplewood/Process-Development-Engineer_R01155761",
    "description": "",
    "salary": "",
    "job_type": "",
    "source_site": "3M Workday",
    "scraped_at": "2025-10-07T10:48:51.641806"
  },
  {
    "title": "Digital Marketing Content Specialist - Sumaré/SP (Região de Campinas)",
    "company": "",
    "location": "",
    "date_posted": "",
    "apply_url": "https://3m.wd1.myworkdayjobs.com/en-US/Search/job/BR-So-Paulo-Sumare/Digital-Shelf-Specialist---Sumar-SP--Regio-de-Campinas-_R01154975",
    "description": "",
    "salary": "",
    "job_type": "",
    "source_site": "3M Workday",
    "scraped_at": "2025-10-07T10:48:51.643716"
  },
  {
    "title": "Digital Marketing Content Specialist - Sumaré/SP (Região de Campinas)",
    "company": "",
    "location": "",
    "date_posted": "",
    "apply_url": "https://3m.wd1.myworkdayjobs.com/en-US/Search/job/BR-So-Paulo-Sumare/Digital-Shelf-Specialist---Sumar-SP--Regio-de-Campinas-_R01154975",
    "description": "",
    "salary": "",
    "job_type": "",
    "source_site": "3M Workday",
    "scraped_at": "2025-10-07T10:48:51.644763"
  },
  {
    "title": "Digital Marketing Content Specialist - Sumaré/SP (Região de Campinas)",
    "company": "",
    "location": "",
    "date_posted": "",
    "apply_url": "https://3m.wd1.myworkdayjobs.com/en-US/Search/job/BR-So-Paulo-Sumare/Digital-Shelf-Specialist---Sumar-SP--Regio-de-Campinas-_R01154975",
    "description": "",
    "salary": "",
    "job_type": "",
    "source_site": "3M Workday",
    "scraped_at": "2025-10-07T10:48:51.645767"
  },
  {
    "title": "Gerente de Cuentas Claves - Division Proteccion Personal",
    "company": "",
    "location": "",
    "date_posted": "",
    "apply_url": "https://3m.wd1.myworkdayjobs.com/en-US/Search/job/PE-Lima/Gerente-de-Cuentas-Claves---Division-Proteccion-Personal_R01156392",
    "description": "",
    "salary": "",
    "job_type": "",
    "source_site": "3M Workday",
    "scraped_at": "2025-10-07T10:48:51.646767"
  },
  {
    "title": "Gerente de Cuentas Claves - Division Proteccion Personal",
    "company": "",
    "location": "",
    "date_posted": "",
    "apply_url": "https://3m.wd1.myworkdayjobs.com/en-US/Search/job/PE-Lima/Gerente-de-Cuentas-Claves---Division-Proteccion-Personal_R01156392",
    "description": "",
    "salary": "",
    "job_type": "",
    "source_site": "3M Workday",
    "scraped_at": "2025-10-07T10:48:51.647767"
  },
  {
    "title": "Gerente de Cuentas Claves - Division Proteccion Personal",
    "company": "",
    "location": "",
    "date_posted": "",
    "apply_url": "https://3m.wd1.myworkdayjobs.com/en-US/Search/job/PE-Lima/Gerente-de-Cuentas-Claves---Division-Proteccion-Personal_R01156392",
    "description": "",
    "salary": "",
    "job_type": "",
    "source_site": "3M Workday",
    "scraped_at": "2025-10-07T10:48:51.648767"
  },
  {
    "title": "Product Development Specialist - Aerospace*",
    "company": "",
    "location": "",
    "date_posted": "",
    "apply_url": "https://3m.wd1.myworkdayjobs.com/en-US/Search/job/US-Minnesota-Maplewood/Product-Development-Specialist---Aerospace-_R01156303",
    "description": "",
    "salary": "",
    "job_type": "",
    "source_site": "3M Workday",
    "scraped_at": "2025-10-07T10:48:51.650741"
  },
  {
    "title": "Product Development Specialist - Aerospace*",
    "company": "",
    "location": "",
    "date_posted": "",
    "apply_url": "https://3m.wd1.myworkdayjobs.com/en-US/Search/job/US-Minnesota-Maplewood/Product-Development-Specialist---Aerospace-_R01156303",
    "description": "",
    "salary": "",
    "job_type": "",
    "source_site": "3M Workday",
    "scraped_at": "2025-10-07T10:48:51.652018"
  },
  {
    "title": "Product Development Specialist - Aerospace*",
    "company": "",
    "location": "",
    "date_posted": "",
    "apply_url": "https://3m.wd1.myworkdayjobs.com/en-US/Search/job/US-Minnesota-Maplewood/Product-Development-Specialist---Aerospace-_R01156303",
    "description": "",
    "salary": "",
    "job_type": "",
    "source_site": "3M Workday",
    "scraped_at": "2025-10-07T10:48:51.653064"
  },
  {
    "title": "VAT and IEPS Certification Specialist, San Luis Potosí",
    "company": "",
    "location": "",
    "date_posted": "",
    "apply_url": "https://3m.wd1.myworkdayjobs.com/en-US/Search/job/MX-San-Luis-Potosi-Sl/VAT-and-IEPS-Certification-Specialist--San-Luis-Potos_R01155977",
    "description": "",
    "salary": "",
    "job_type": "",
    "source_site": "3M Workday",
    "scraped_at": "2025-10-07T10:48:51.656326"
  },
  {
    "title": "VAT and IEPS Certification Specialist, San Luis Potosí",
    "company": "",
    "location": "",
    "date_posted": "",
    "apply_url": "https://3m.wd1.myworkdayjobs.com/en-US/Search/job/MX-San-Luis-Potosi-Sl/VAT-and-IEPS-Certification-Specialist--San-Luis-Potos_R01155977",
    "description": "",
    "salary": "",
    "job_type": "",
    "source_site": "3M Workday",
    "scraped_at": "2025-10-07T10:48:51.657319"
  },
  {
    "title": "VAT and IEPS Certification Specialist, San Luis Potosí",
    "company": "",
    "location": "",
    "date_posted": "",
    "apply_url": "https://3m.wd1.myworkdayjobs.com/en-US/Search/job/MX-San-Luis-Potosi-Sl/VAT-and-IEPS-Certification-Specialist--San-Luis-Potos_R01155977",
    "description": "",
    "salary": "",
    "job_type": "",
    "source_site": "3M Workday",
    "scraped_at": "2025-10-07T10:48:51.658313"
  },
  {
    "title": "Senior Key Account Manager, Consumer Business Group(General Trade/ Office Supplies)",
    "company": "",
    "location": "",
    "date_posted": "",
    "apply_url": "https://3m.wd1.myworkdayjobs.com/en-US/Search/job/SG-Singapore/Senior-Key-Account-Manager--Consumer-Business-Group-General-Trade--Office-Supplies-_R01156564",
    "description": "",
    "salary": "",
    "job_type": "",
    "source_site": "3M Workday",
    "scraped_at": "2025-10-07T10:48:51.660338"
  },
  {
    "title": "Senior Key Account Manager, Consumer Business Group(General Trade/ Office Supplies)",
    "company": "",
    "location": "",
    "date_posted": "",
    "apply_url": "https://3m.wd1.myworkdayjobs.com/en-US/Search/job/SG-Singapore/Senior-Key-Account-Manager--Consumer-Business-Group-General-Trade--Office-Supplies-_R01156564",
    "description": "",
    "salary": "",
    "job_type": "",
    "source_site": "3M Workday",
    "scraped_at": "2025-10-07T10:48:51.661332"
  },
  {
    "title": "Senior Key Account Manager, Consumer Business Group(General Trade/ Office Supplies)",
    "company": "",
    "location": "",
    "date_posted": "",
    "apply_url": "https://3m.wd1.myworkdayjobs.com/en-US/Search/job/SG-Singapore/Senior-Key-Account-Manager--Consumer-Business-Group-General-Trade--Office-Supplies-_R01156564",
    "description": "",
    "salary": "",
    "job_type": "",
    "source_site": "3M Workday",
    "scraped_at": "2025-10-07T10:48:51.662601"
  },
  {
    "title": "Area Sales Manager",
    "company": "",
    "location": "",
    "date_posted": "",
    "apply_url": "https://3m.wd1.myworkdayjobs.com/en-US/Search/job/IN-Pune/Area-Sales-Manager_R01155793",
    "description": "",
    "salary": "",
    "job_type": "",
    "source_site": "3M Workday",
    "scraped_at": "2025-10-07T10:48:51.663646"
  },
  {
    "title": "Area Sales Manager",
    "company": "",
    "location": "",
    "date_posted": "",
    "apply_url": "https://3m.wd1.myworkdayjobs.com/en-US/Search/job/IN-Pune/Area-Sales-Manager_R01155793",
    "description": "",
    "salary": "",
    "job_type": "",
    "source_site": "3M Workday",
    "scraped_at": "2025-10-07T10:48:51.664650"
  },
  {
    "title": "Area Sales Manager",
    "company": "",
    "location": "",
    "date_posted": "",
    "apply_url": "https://3m.wd1.myworkdayjobs.com/en-US/Search/job/IN-Pune/Area-Sales-Manager_R01155793",
    "description": "",
    "salary": "",
    "job_type": "",
    "source_site": "3M Workday",
    "scraped_at": "2025-10-07T10:48:51.666654"
  }
]